Metadata-Version: 2.1
Name: masciitable
Version: 1.0.0
Summary: MXCHIP ASCII Table Convertor
Home-page: https://github.com/smartsnow/masciitable
Author: Snow Yang
Author-email: yangsw@mxchip.com
License: UNKNOWN
Keywords: MXCHIP ASCII Table Convertor
Platform: UNKNOWN
Classifier: Development Status :: 4 - Beta
Classifier: Intended Audience :: Developers
Classifier: Topic :: Software Development :: Build Tools
Classifier: Programming Language :: Python :: 3.5
Classifier: Programming Language :: Python :: 3.6
Classifier: Programming Language :: Python :: 3.7
Requires-Python: >=3.5
